[
  {
    "id": "page-metadata",
    "fields": [
      {
        "component": "container",
        "label": "Fieldset",
        "fields": [
          {
            "component": "text",
            "valueType": "string",
            "name": "title",
            "label": "Title",
            "value": ""
          },
          {
            "component": "text",
            "valueType": "string",
            "name": "description",
            "label": "Description",
            "value": ""
          },
          {
            "component": "text",
            "valueType": "string",
            "name": "keywords",
            "multi": true,
            "label": "Keywords",
            "value": ""
          },
          {
            "component": "text",
            "valueType": "string",
            "name": "article:Tag",
            "label": "article:tag",
            "value": ""
          },
          {
            "component": "text",
            "valueType": "string",
            "name": "path",
            "label": ":path",
            "value": ""
          },
          {
            "component": "text",
            "valueType": "string",
            "name": "template",
            "label": "Template",
            "value": ""
          },
          {
            "component": "text",
            "valueType": "string",
            "name": "brand",
            "label": "Brand",
            "value": ""
          },
          {
            "component": "date-time",
            "valueType": "date-time",
            "name": "creationdate",
            "label": "Creation Date",
            "placeholder": "YYYY-MM-DD",
            "displayFormat": null,
            "valueFormat": null,
            "value": ""
          },
          {
            "component": "date-time",
            "valueType": "date-time",
            "name": "updatedate",
            "label": "Update Date",
            "placeholder": "YYYY-MM-DD",
            "displayFormat": null,
            "valueFormat": null,
            "value": ""
          },
          {
            "component": "text",
            "valueType": "string",
            "name": "fullcategory",
            "label": "Full Category",
            "value": ""
          },
          {
            "component": "text",
            "valueType": "string",
            "name": "viewport",
            "label": "View Port",
            "value": ""
          }
        ]
      }
    ]
  },
  {
    "id": "image",
    "fields": [
      {
        "component": "reference",
        "name": "image",
        "label": "Image",
        "multi": false
      },
      {
        "component": "text",
        "name": "imageAlt",
        "label": "Alt Text"
      }
    ]
  },
  {
    "id": "title",
    "fields": [
      {
        "component": "text",
        "name": "title",
        "label": "Title"
      },
      {
        "component": "select",
        "name": "titleType",
        "label": "Title Type",
        "options": [
          {
            "name": "h1",
            "value": "h1"
          },
          {
            "name": "h2",
            "value": "h2"
          },
          {
            "name": "h3",
            "value": "h3"
          },
          {
            "name": "h4",
            "value": "h4"
          },
          {
            "name": "h5",
            "value": "h5"
          },
          {
            "name": "h6",
            "value": "h6"
          }
        ]
      }
    ]
  },
  {
    "id": "button",
    "fields": [
      {
        "component": "aem-content",
        "name": "link",
        "label": "Link"
      },
      {
        "component": "text",
        "name": "linkText",
        "label": "Text"
      },
      {
        "component": "text",
        "name": "linkTitle",
        "label": "Title"
      },
      {
        "component": "select",
        "name": "linkType",
        "label": "Type",
        "options": [
          {
            "name": "default",
            "value": ""
          },
          {
            "name": "primary",
            "value": "primary"
          },
          {
            "name": "secondary",
            "value": "secondary"
          }
        ]
      }
    ]
  },
  {
    "id": "section",
    "fields": [
      {
        "component": "multiselect",
        "name": "style",
        "label": "Style",
        "options": [
          {
            "name": "Highlight",
            "value": "highlight"
          }
        ]
      }
    ]
  },
  {
    "id": "accordion-container",
    "fields": [
      {
        "component": "text",
        "valueType": "string",
        "name": "accordion_container_title",
        "value": "",
        "label": "Super Title"
      }
    ]
  },
  {
    "id": "accordion-item",
    "fields": [
      {
        "component": "text",
        "valueType": "string",
        "name": "item_title",
        "value": "",
        "label": "Title"
      },
      {
        "component": "richtext",
        "valueType": "string",
        "name": "item_description",
        "value": "",
        "label": "Description"
      }
    ]
  },
  {
    "id": "articleinfo",
    "fields": [
      {
        "component": "date",
        "valueType": "string",
        "name": "publishDate",
        "label": "Publish Date",
        "value": ""
      },
      {
        "component": "number",
        "valueType": "number",
        "name": "readingTime",
        "label": "Reading Time",
        "value": ""
      }
    ]
  },
  {
    "id": "articles-list",
    "fields": [
      {
        "component": "text",
        "valueType": "string",
        "name": "title",
        "value": "",
        "label": "Title"
      }
    ]
  },
  {
    "id": "banner",
    "fields": [
      {
        "component": "text",
        "valueType": "string",
        "name": "banner",
        "value": "",
        "label": "Banner"
      },
      {
        "component": "text",
        "valueType": "string",
        "name": "description",
        "value": "",
        "label": "Description"
      }
    ]
  },
  {
    "id": "body-banner",
    "fields": [
      {
        "component": "text",
        "valueType": "string",
        "name": "title1",
        "value": "",
        "label": "Title"
      },
      {
        "component": "text",
        "valueType": "string",
        "name": "title2",
        "value": "",
        "label": "Heading"
      },
      {
        "component": "text",
        "valueType": "string",
        "name": "title3",
        "value": "",
        "label": "Sub Heading"
      },
      {
        "component": "richtext",
        "valueType": "string",
        "name": "description",
        "value": "",
        "label": "Description"
      },
      {
        "component": "reference",
        "valueType": "string",
        "name": "fileReference",
        "label": "Image",
        "multi": true
      },
      {
        "component": "aem-content",
        "name": "link",
        "label": "Link"
      },
      {
        "component": "boolean",
        "name": "bodyBannerLinkTarget",
        "value": false,
        "label": "Open link in new tab?"
      },
      {
        "component": "text",
        "valueType": "string",
        "name": "linklabel",
        "value": "",
        "label": "Link Label"
      },
      {
        "component": "text",
        "valueType": "string",
        "name": "right-bg-color",
        "value": "",
        "label": "Right-Bg-Color"
      }
    ]
  },
  {
    "id": "breadcrumb",
    "fields": [
      {
        "component": "aem-content",
        "name": "link",
        "label": "Link"
      }
    ]
  },
  {
    "id": "cards",
    "fields": [
      {
        "component": "multiselect",
        "valueType": "string",
        "name": "classes",
        "value": "",
        "label": "Block Options",
        "options": [
          {
            "name": "Article Card",
            "value": "articlecard"
          },
          {
            "name": "4 Columns",
            "value": "cols-4"
          }
        ]
      }
    ]
  },
  {
    "id": "cards-item",
    "fields": [
      {
        "component": "reference",
        "valueType": "string",
        "name": "fileReference",
        "label": "Image",
        "multi": false
      },
      {
        "component": "text",
        "valueType": "string",
        "name": "card_alt",
        "value": "Danaher Corporation",
        "label": "Alt Text"
      },
      {
        "component": "text",
        "valueType": "string",
        "name": "card_opco",
        "value": "",
        "label": "Opco"
      },
      {
        "component": "text",
        "valueType": "string",
        "name": "card_title",
        "value": "",
        "label": "Title"
      },
      {
        "component": "select",
        "name": "card_titleType",
        "value": "h1",
        "label": "Type",
        "valueType": "string",
        "options": [
          {
            "name": "h1",
            "value": "h1"
          },
          {
            "name": "h2",
            "value": "h2"
          },
          {
            "name": "h3",
            "value": "h3"
          },
          {
            "name": "h4",
            "value": "h4"
          },
          {
            "name": "h5",
            "value": "h5"
          },
          {
            "name": "h6",
            "value": "h6"
          }
        ]
      },
      {
        "component": "richtext",
        "valueType": "string",
        "name": "card_description",
        "value": "",
        "label": "Description"
      },
      {
        "component": "text",
        "valueType": "string",
        "name": "card_href",
        "value": "",
        "label": "Link"
      },
      {
        "component": "text",
        "valueType": "string",
        "name": "card_hrefText",
        "value": "",
        "label": "Link Text"
      }
    ]
  },
  {
    "id": "columns",
    "fields": [
      {
        "component": "multiselect",
        "name": "classes",
        "value": "",
        "label": "Style",
        "valueType": "string"
      },
      {
        "component": "text",
        "valueType": "number",
        "name": "columns",
        "value": "",
        "label": "Columns"
      },
      {
        "component": "text",
        "valueType": "number",
        "name": "rows",
        "value": "",
        "label": "Rows"
      }
    ]
  },
  {
    "id": "dual-carousel",
    "fields": [
      {
        "component": "text",
        "valueType": "string",
        "name": "leftCarouselTitle",
        "value": "",
        "label": "Left Carousel Title"
      },
      {
        "component": "text",
        "valueType": "string",
        "name": "leftCarouselLinkLabel",
        "value": "",
        "label": "Left Carousel Link Label"
      },
      {
        "component": "text",
        "valueType": "string",
        "name": "leftCarouselProductId",
        "value": "",
        "label": "Left Carousel Product IDs"
      },
      {
        "component": "text",
        "valueType": "string",
        "name": "rightCarouseTitle",
        "value": "",
        "label": "Right Carousel Title"
      },
      {
        "component": "text",
        "valueType": "string",
        "name": "rightCarouselLinkLabel",
        "value": "",
        "label": "Right Carousel Link Label"
      },
      {
        "component": "text",
        "valueType": "string",
        "name": "rightCarouselProductId",
        "value": "",
        "label": "Right Carousel Product IDs"
      }
    ]
  },
  {
    "id": "insight",
    "fields": [
      {
        "component": "text",
        "valueType": "string",
        "name": "titleText",
        "value": "",
        "label": "Title"
      },
      {
        "component": "richtext",
        "valueType": "string",
        "name": "description",
        "value": "",
        "label": "Description"
      }
    ]
  },
  {
    "id": "insight-item",
    "fields": [
      {
        "component": "text",
        "valueType": "string",
        "name": "lefttitle",
        "value": "",
        "label": "Title"
      },
      {
        "component": "text",
        "valueType": "string",
        "name": "leftDes",
        "value": "",
        "label": "Description"
      },
      {
        "component": "select",
        "name": "insightItemLinkType",
        "label": "Link Type",
        "required": true,
        "valueType": "string",
        "options": [
          {
            "name": "modal",
            "value": "modal"
          },
          {
            "name": "url",
            "value": "url"
          }
        ]
      },
      {
        "component": "aem-content",
        "name": "insight_link",
        "label": "Link Url"
      },
      {
        "component": "boolean",
        "name": "insightlinkTarget",
        "valueType": "boolean",
        "value": false,
        "label": "Open link in new tab?"
      },
      {
        "component": "text",
        "valueType": "string",
        "name": "linklabel",
        "value": "",
        "label": "Link Label"
      },
      {
        "component": "reference",
        "valueType": "string",
        "name": "fileReference",
        "label": "Icon"
      }
    ]
  },
  {
    "id": "learn-more",
    "fields": [
      {
        "component": "text",
        "valueType": "string",
        "name": "title",
        "value": "",
        "label": "Title"
      },
      {
        "component": "richtext",
        "valueType": "string",
        "name": "brandaddress",
        "value": "",
        "label": "Brand Address"
      },
      {
        "component": "richtext",
        "valueType": "string",
        "name": "callDescription",
        "value": "",
        "label": "Call-Description"
      },
      {
        "component": "richtext",
        "valueType": "string",
        "name": "browseDescription",
        "value": "",
        "label": "Browse-Description"
      }
    ]
  },
  {
    "id": "offer-advertisement",
    "fields": [
      {
        "component": "text",
        "valueType": "string",
        "name": "offer_advertisement_title",
        "value": "",
        "label": "Offer Title"
      },
      {
        "component": "select",
        "name": "adLinkType",
        "label": "Link Type",
        "required": true,
        "valueType": "string",
        "options": [
          {
            "name": "modal",
            "value": "modal"
          },
          {
            "name": "url",
            "value": "url"
          }
        ]
      },
      {
        "component": "text",
        "valueType": "string",
        "name": "offer_text",
        "value": "",
        "label": "Offer Text Link"
      },
      {
        "component": "aem-content",
        "name": "offer_link",
        "label": "Link"
      },
      {
        "component": "boolean",
        "name": "subscribe",
        "value": false,
        "label": "Open Read More link in new tab"
      }
    ]
  },
  {
    "id": "offer-banner",
    "fields": [
      {
        "component": "text",
        "valueType": "string",
        "name": "offer_title",
        "value": "",
        "label": "Title"
      },
      {
        "component": "reference",
        "valueType": "string",
        "name": "fileReference",
        "label": "brand-Image",
        "multi": false
      },
      {
        "component": "aem-content",
        "name": "link",
        "label": "Offer Link"
      },
      {
        "component": "boolean",
        "name": "linkTarget",
        "valueType": "boolean",
        "value": false,
        "label": "Open link in new tab?"
      },
      {
        "component": "text",
        "name": "linkLabel",
        "label": "Offer Link Label"
      },
      {
        "component": "text",
        "valueType": "string",
        "name": "bg-color",
        "value": "",
        "label": "Bg-Color"
      }
    ]
  },
  {
    "id": "opco-banner",
    "fields": [
      {
        "component": "text",
        "valueType": "string",
        "name": "opcoBannerTitle",
        "value": "",
        "label": "Banner Title"
      },
      {
        "component": "text",
        "valueType": "string",
        "name": "opcoBannerHeading",
        "value": "",
        "label": "Banner Heading"
      },
      {
        "component": "richtext",
        "valueType": "string",
        "name": "opcoBannerDescription",
        "value": "",
        "label": "Banner Description"
      },
      {
        "component": "reference",
        "valueType": "string",
        "name": "opcoBannerImage",
        "label": "Banner Image",
        "multi": false
      },
      {
        "component": "aem-content",
        "name": "opcoBannerButtonUrl",
        "label": "Banner Button Url"
      },
      {
        "component": "boolean",
        "name": "opcoBannerButtonTarget",
        "valueType": "boolean",
        "value": false,
        "label": "Open link in new tab?"
      },
      {
        "component": "text",
        "valueType": "string",
        "name": "opcoBannerButtonLabel",
        "value": "",
        "label": "Banner Button Label"
      }
    ]
  },
  {
    "id": "opco-banner-item",
    "fields": [
      {
        "component": "text",
        "valueType": "string",
        "name": "opcoBannerItemTitle",
        "value": "",
        "label": "Title"
      },
      {
        "component": "text",
        "valueType": "string",
        "name": "opcoBannerItemSubHeading",
        "value": "",
        "label": "Sub Heading"
      },
      {
        "component": "richtext",
        "valueType": "string",
        "name": "opcoBannerItemDescription",
        "value": "",
        "label": "Description"
      },
      {
        "component": "reference",
        "valueType": "string",
        "name": "opcoBannerItemImage",
        "label": "Image",
        "multi": false
      },
      {
        "component": "reference",
        "valueType": "string",
        "name": "opcoBannerItemBgImage",
        "label": "Background Image",
        "multi": false
      },
      {
        "component": "aem-content",
        "name": "opcoBannerItemButtonUrl",
        "label": "Button Url"
      },
      {
        "component": "boolean",
        "name": "opcoBannerItemButtonTarget",
        "value": false,
        "label": "Open link in new tab?"
      },
      {
        "component": "text",
        "valueType": "string",
        "name": "opcoBannerItemButtonLabel",
        "value": "",
        "label": "Button Label"
      }
    ]
  },
  {
    "id": "opco-grid",
    "fields": [
      {
        "component": "multiselect",
        "valueType": "string",
        "name": "classes",
        "value": "",
        "label": "Block Options",
        "options": [
          {
            "name": "Opco Grid",
            "value": "opco-grid"
          },
          {
            "name": "4 Columns",
            "value": "cols-4"
          }
        ]
      }
    ]
  },
  {
    "id": "opco-grid-item",
    "fields": [
      {
        "component": "reference",
        "valueType": "string",
        "name": "fileReference",
        "label": "Image",
        "multi": false
      },
      {
        "component": "text",
        "valueType": "string",
        "name": "cardAlt",
        "label": "Alt Text"
      },
      {
        "component": "text",
        "valueType": "string",
        "name": "cardTitle",
        "label": "Title"
      },
      {
        "component": "richtext",
        "valueType": "string",
        "name": "cardDescription",
        "label": "Description"
      },
      {
        "component": "aem-content",
        "valueType": "string",
        "name": "cardHref",
        "label": "Link"
      },
      {
        "component": "select",
        "name": "cardLinkTarget",
        "label": "Open link in new tab?",
        "valueType": "string",
        "options": [
          {
            "name": "yes",
            "value": "yes"
          },
          {
            "name": "no",
            "value": "no"
          }
        ]
      },
      {
        "component": "text",
        "valueType": "string",
        "name": "cardHrefText",
        "label": "Link Text"
      }
    ]
  },
  {
    "id": "page-tabs",
    "fields": []
  },
  {
    "id": "product-banner",
    "fields": [
      {
        "component": "text",
        "valueType": "string",
        "name": "heading",
        "value": "",
        "label": "Heading"
      },
      {
        "component": "text",
        "valueType": "string",
        "name": "button_text",
        "value": "",
        "label": "Button Text"
      },
      {
        "component": "aem-content",
        "name": "btn_link",
        "label": "Button Link"
      },
      {
        "component": "richtext",
        "valueType": "string",
        "name": "short_description",
        "value": "",
        "label": "Short description"
      },
      {
        "component": "reference",
        "valueType": "string",
        "name": "banner_image",
        "label": "Image",
        "multi": false
      },
      {
        "component": "richtext",
        "valueType": "string",
        "name": "long_desc",
        "value": "",
        "label": "Long Description"
      }
    ]
  },
  {
    "id": "product-categories",
    "fields": [
      {
        "component": "text",
        "valueType": "string",
        "name": "prod_category_id",
        "value": "",
        "label": "Product Category ID"
      },
      {
        "component": "text",
        "valueType": "string",
        "name": "title",
        "value": "",
        "label": "Title"
      },
      {
        "component": "text",
        "valueType": "string",
        "name": "brand",
        "value": "",
        "label": "Brand"
      }
    ]
  },
  {
    "id": "product-category-list",
    "fields": [
      {
        "component": "text",
        "valueType": "string",
        "name": "title",
        "value": "",
        "label": "Title"
      }
    ]
  },
  {
    "id": "product-category",
    "fields": [
      {
        "component": "text",
        "valueType": "string",
        "name": "title",
        "value": "",
        "label": "Title"
      }
    ]
  },
  {
    "id": "product-family",
    "fields": [
      {
        "component": "text",
        "valueType": "string",
        "name": "family_id",
        "value": "",
        "label": "Family ID"
      }
    ]
  },
  {
    "id": "product-hero-content",
    "fields": [
      {
        "component": "text",
        "valueType": "string",
        "name": "prod_hero_id",
        "value": "",
        "label": "Product Hero ID"
      },
      {
        "component": "text",
        "valueType": "string",
        "name": "prod_hero_title",
        "value": "",
        "label": "Title"
      },
      {
        "component": "text",
        "valueType": "string",
        "name": "prod_hero_description",
        "value": "",
        "label": "Description"
      },
      {
        "component": "text",
        "valueType": "string",
        "name": "readMore_label",
        "value": "",
        "label": "Read More Label"
      },
      {
        "component": "aem-content",
        "name": "readMore_link",
        "label": "Read More Link"
      },
      {
        "component": "boolean",
        "name": "subscribe",
        "value": false,
        "label": "Open Read More link in new tab"
      }
    ]
  },
  {
    "id": "product-hero",
    "fields": []
  },
  {
    "id": "product-info-list",
    "fields": [
      {
        "component": "text",
        "valueType": "string",
        "name": "prod_info_title",
        "value": "",
        "label": "Title"
      },
      {
        "component": "richtext",
        "valueType": "string",
        "name": "prod_info_description",
        "value": "",
        "label": "Description"
      }
    ]
  },
  {
    "id": "recent-articles",
    "fields": []
  },
  {
    "id": "related-category",
    "fields": [
      {
        "component": "text",
        "valueType": "string",
        "name": "title",
        "value": "",
        "label": "Title"
      },
      {
        "component": "text",
        "valueType": "string",
        "name": "productid",
        "value": "",
        "label": "Category Title(comma separated)"
      }
    ]
  },
  {
    "id": "separator-line",
    "fields": [
      {
        "component": "text",
        "valueType": "string",
        "name": "separatorHeight",
        "value": "1",
        "label": "Separator Height (in px)"
      },
      {
        "component": "text",
        "valueType": "string",
        "name": "bg-color",
        "value": "#D1D5DB",
        "label": "Bg-Color"
      }
    ]
  },
  {
    "id": "shop-featured-products",
    "fields": [
      {
        "component": "text",
        "valueType": "string",
        "name": "sectionHeading",
        "value": "",
        "label": "Section Heading"
      }
    ]
  },
  {
    "id": "shop-featured-products-item",
    "fields": [
      {
        "component": "text",
        "valueType": "string",
        "name": "brandTitle",
        "value": "",
        "label": "Brand Title"
      },
      {
        "component": "text",
        "valueType": "string",
        "name": "productTitle",
        "value": "",
        "label": "Product Title"
      },
      {
        "component": "text",
        "valueType": "string",
        "name": "productSubHeading",
        "value": "",
        "label": "Product Sub Heading"
      },
      {
        "component": "richtext",
        "valueType": "string",
        "name": "productDescription",
        "value": "",
        "label": "Product Description"
      },
      {
        "component": "reference",
        "valueType": "string",
        "name": "fileReference",
        "label": "Product Image",
        "multi": false
      },
      {
        "component": "text",
        "valueType": "string",
        "name": "productButtonLabel",
        "label": "Button Label"
      },
      {
        "component": "aem-content",
        "valueType": "string",
        "name": "productButtonURL",
        "value": "",
        "label": "Button URL"
      },
      {
        "component": "boolean",
        "name": "productButtonTarget",
        "value": false,
        "label": "Open link in new tab?"
      },
      {
        "component": "text",
        "valueType": "string",
        "name": "bgColor",
        "value": "#4000A5",
        "label": "Bg Color"
      }
    ]
  },
  {
    "id": "simple-text",
    "fields": [
      {
        "component": "richtext",
        "valueType": "string",
        "name": "leftText",
        "value": "",
        "label": "Left Text"
      },
      {
        "component": "richtext",
        "valueType": "string",
        "name": "rightText",
        "value": "",
        "label": "Right Text"
      }
    ]
  },
  {
    "id": "tabs-container",
    "fields": [
      {
        "component": "text",
        "name": "containerId",
        "value": "",
        "label": "Container Id",
        "valueType": "string"
      }
    ]
  },
  {
    "id": "tiny-carousel",
    "fields": [
      {
        "component": "text",
        "valueType": "string",
        "name": "titleText",
        "value": "",
        "label": "Title Text"
      }
    ],
    "multi": true
  },
  {
    "id": "tiny-carousel-item",
    "fields": [
      {
        "component": "text",
        "valueType": "string",
        "name": "product_id",
        "value": "",
        "label": "Product ID"
      },
      {
        "component": "text",
        "valueType": "string",
        "name": "card_hrefText",
        "value": "",
        "label": "Link Text"
      }
    ]
  },
  {
    "id": "top-purchased-products",
    "fields": [
      {
        "component": "text",
        "valueType": "string",
        "name": "titleText",
        "value": "",
        "label": "Title"
      },
      {
        "component": "text",
        "valueType": "string",
        "name": "productid",
        "value": "",
        "label": "Product IDs (comma separated)"
      }
    ]
  },
  {
    "id": "top-selling",
    "fields": [
      {
        "component": "text",
        "valueType": "string",
        "name": "titleText",
        "value": "",
        "label": "Title Text"
      },
      {
        "component": "text",
        "valueType": "string",
        "name": "card_hrefText",
        "value": "",
        "label": "Link Text"
      },
      {
        "component": "aem-content",
        "valueType": "string",
        "name": "card_hrefUrl",
        "value": "",
        "label": "Link URL"
      },
      {
        "component": "boolean",
        "name": "subscribe",
        "value": false,
        "label": "Open link in new tab"
      },
      {
        "component": "text",
        "valueType": "string",
        "name": "productid",
        "value": "",
        "label": "Product IDs(comma separated)"
      }
    ]
  }
]