{
  "definitions": [
    {
      "title": "Columns",
      "id": "columns",
      "plugins": {
        "xwalk": {
          "page": {
            "resourceType": "core/franklin/components/columns/v1/columns",
            "template": {
              "columns": "2",
              "rows": "1"
            }
          }
        }
      }
    }
  ],
  "models": [
    {
      "id": "columns",
      "fields": [
        {
          "component": "multiselect",
          "name": "classes",
          "label": "Style",
          "valueType": "string",
          "options": [
            { "name": "70/30 Split", "value": "seventythirty" },
            { "name": "30/70 Split", "value": "thirtyseventy" },
            { "name": "50/50 Split", "value": "fiftyfifty" },
            { "name": "Text White", "value": "text-white" },
            { "name": "Bottom Border Right", "value": "bottom-border-right" },
            { "name": "Background Color Right", "value": "bg-color-right" }
          ]
        },
        {
          "component": "select",
          "name": "columns",
          "label": "Number of Columns",
          "valueType": "string",
          "options": [
            { "name": "1 Column", "value": "columns-1-cols" },
            { "name": "2 Columns", "value": "columns-2-cols" },
            { "name": "3 Columns", "value": "columns-3-cols" }
          ]
        },
        {
          "component": "text",
          "name": "rows",
          "label": "Rows",
          "valueType": "number",
          "value": ""
        }
      ]
    }
  ],
  "filters": [
    {
      "id": "columns",
      "components": [
        "column"
      ]
    },
    {
      "id": "column",
      "components": [
        "text",
        "image",
        "button",
        "title",
        "article-info-new",
        "embed",
        "form"
      ]
    }
  ]
}
